xyz_tenant/__init__.py
xyz_tenant/apis.py
xyz_tenant/apps.py
xyz_tenant/choices.py
xyz_tenant/middleware.py
xyz_tenant/models.py
xyz_tenant/receivers.py
xyz_tenant/tasks.py
xyz_tenant/migrations/0001_initial.py
xyz_tenant/migrations/__init__.py
xyz_tenant-0.0.1.dist-info/METADATA
xyz_tenant-0.0.1.dist-info/WHEEL
xyz_tenant-0.0.1.dist-info/top_level.txt
xyz_tenant-0.0.1.dist-info/RECORD
