Metadata-Version: 2.1
Name: xyz-tenant
Version: 0.0.1
Summary: tenant
Home-page: https://github.com/szuprefix/py-xyz-tenant
Author: szuprefix
Author-email: szuprefix@126.com
License: MIT
Platform: UNKNOWN
Classifier: Environment :: Web Environment
Classifier: Intended Audience :: Developers
Classifier: Operating System :: OS Independent
Classifier: Topic :: Text Processing :: Indexing
Classifier: Topic :: Utilities
Classifier: Topic :: Internet
Classifier: Topic :: Software Development :: Libraries :: Python Modules
Classifier: Programming Language :: Python
Classifier: Programming Language :: Python :: 2
Classifier: Programming Language :: Python :: 2.7
Requires-Dist: django (>=1.11.2)
Requires-Dist: django-tenant-schemas (>=1.10.0)
